sortium/__init__.py
sortium/cli.py
sortium/config.py
sortium/file_utils.py
sortium/sorter.py
sortium-2.2.3.dist-info/licenses/LICENSE
tests/README.md
tests/__init__.py
tests/conftest.py
tests/test_cli.py
tests/test_file_utils.py
tests/test_sorter.py
sortium-2.2.3.dist-info/METADATA
sortium-2.2.3.dist-info/WHEEL
sortium-2.2.3.dist-info/entry_points.txt
sortium-2.2.3.dist-info/top_level.txt
sortium-2.2.3.dist-info/RECORD
