Metadata-Version: 2.4
Name: Sortium
Version: 2.2.3
Summary: A utility to sort files by type and date.
Author-email: Sarthak Goyal <sarthakgoyal487@gmail.com>
License: MIT
Project-URL: repository, https://github.com/Sarthak-G0yal/Sortium
Project-URL: documentation, https://sarthak-g0yal.github.io/Sortium/
Classifier: License :: OSI Approved :: GNU General Public License v3 (GPLv3)
Classifier: Operating System :: OS Independent
Classifier: Intended Audience :: Developers
Classifier: Intended Audience :: End Users/Desktop
Classifier: Topic :: Utilities
Classifier: Topic :: System :: Filesystems
Requires-Python: >=3.10
License-File: LICENSE
Provides-Extra: docs
Requires-Dist: sphinx; extra == "docs"
Requires-Dist: pydata-sphinx-theme==0.15.4; extra == "docs"
Provides-Extra: test
Requires-Dist: pytest; extra == "test"
Requires-Dist: pytest-cov; extra == "test"
Dynamic: license-file
